symplectic_koopman_operator/__init__.py
symplectic_koopman_operator/functional.py
symplectic_koopman_operator/symplectic_koopman_operator.py
symplectic_koopman_operator-0.0.2.dist-info/METADATA
symplectic_koopman_operator-0.0.2.dist-info/WHEEL
symplectic_koopman_operator-0.0.2.dist-info/licenses/LICENSE
symplectic_koopman_operator-0.0.2.dist-info/RECORD
