Metadata-Version: 2.4
Name: symplectic-koopman-operator
Version: 0.0.2
Summary: Structure for creating Koopman operators through training symplectic PyTorch neural networks
Project-URL: Homepage, https://github.com/anderske-msu/symplectic-koopman-operator
Project-URL: Bug Tracker, https://github.com/anderske-msu/symplectic-koopman-operator/issues
Author-email: Kelly Anderson <kjanderson24@proton.me>
License:                     GNU GENERAL PUBLIC LICENSE
License-File: LICENSE
Classifier: License :: OSI Approved :: GNU General Public License v3 (GPLv3)
Classifier: License :: OSI Approved :: GNU General Public License v3 or later (GPLv3+)
Classifier: Programming Language :: Python :: 3
Classifier: Programming Language :: Python :: 3.10
Classifier: Programming Language :: Python :: 3.11
Requires-Python: >=3.10
Requires-Dist: sympnetstorch
Requires-Dist: torch
